 [
    { "name": "John Doe", "location": "United States", "jobRole": "Software Developer" },
    { "name": "Jane Smith", "location": "Canada", "jobRole": "UX Designer" },
    { "name": "David Johnson", "location": "United Kingdom", "jobRole": "Data Analyst" },
    { "name": "Emily Wilson", "location": "Australia", "jobRole": "Front-end Developer" },
    { "name": "Michael Brown", "location": "India", "jobRole": "Full Stack Developer" },
    { "name": "Maria Garcia", "location": "Spain", "jobRole": "UI Designer" },
    { "name": "Andreas Müller", "location": "Germany", "jobRole": "Graphic Designer" },
    { "name": "Sophie Dupont", "location": "France", "jobRole": "Marketing Manager" },
    { "name": "Luca Rossi", "location": "Italy", "jobRole": "Content Writer" },
    { "name": "Marta Hernandez", "location": "Mexico", "jobRole": "Social Media Manager" },
    { "name": "Mohammed Ali", "location": "Egypt", "jobRole": "Sales Representative" },
    { "name": "Satoshi Yamamoto", "location": "Japan", "jobRole": "Account Manager" },
    { "name": "Chen Wei", "location": "China", "jobRole": "Financial Analyst" },
    { "name": "Anna Kowalska", "location": "Poland", "jobRole": "Human Resources Manager" },
    { "name": "Ravi Patel", "location": "India", "jobRole": "Operations Manager" },
    { "name": "Seo-hyun Kim", "location": "South Korea", "jobRole": "Customer Service Representative" },
    { "name": "Anastasia Ivanova", "location": "Russia", "jobRole": "Event Planner" },
    { "name": "Luis González", "location": "Mexico", "jobRole": "Logistics Coordinator" },
    { "name": "Jorge Silva", "location": "Brazil", "jobRole": "Supply Chain Analyst" },
    { "name": "Sarah Nguyen", "location": "Vietnam", "jobRole": "Research Analyst" },
    { "name": "Lucas Santos", "location": "Brazil", "jobRole": "Business Development Manager" },
    { "name": "Fernanda Costa", "location": "Brazil", "jobRole": "UX Researcher" },
    { "name": "Seung-ho Park", "location": "South Korea", "jobRole": "Mobile App Developer" },
    { "name": "Li Wei", "location": "China", "jobRole": "Systems Administrator" },
    { "name": "Olga Ivanova", "location": "Russia", "jobRole": "UI Developer" },
    { "name": "Tomasz Nowak", "location": "Poland", "jobRole": "IT Consultant" },
    { "name": "Gabriel Fernandez", "location": "Argentina", "jobRole": "Network Engineer" },
    { "name": "Ayu Putri", "location": "Indonesia", "jobRole": "Data Engineer" },
    { "name": "Ryu Ji-hoon", "location": "South Korea", "jobRole": "SEO Specialist" },
    { "name": "Mia Müller", "location": "Germany", "jobRole": "Video Editor" },
    { "name": "Elena Popescu", "location": "Romania", "jobRole": "Product Designer" },
    { "name": "Marcelo Silva", "location": "Brazil", "jobRole": "E-commerce Manager" },
    { "name": "Alexandra Petrova", "location": "Russia", "jobRole": "Digital Marketing Specialist" },
    { "name": "Kenta Tanaka", "location": "Japan", "jobRole": "Artificial Intelligence Engineer" },
    { "name": "Andrzej Kowalczyk", "location": "Poland", "jobRole": "Database Developer" },
    { "name": "Siti Utami", "location": "Indonesia", "jobRole": "IT Project Manager" },
    { "name": "Kim Min-ji", "location": "South Korea", "jobRole": "UX Designer" },
    { "name": "Gustavo Hernandez", "location": "Mexico", "jobRole": "Software Developer" },
    { "name": "Julia Rossi", "location": "Italy", "jobRole": "Data Analyst" },
    { "name": "Mohammed Ahmed", "location": "Egypt", "jobRole": "Front-end Developer" },
    { "name": "Léa Dubois", "location": "France", "jobRole": "Product Manager" },
    { "name": "Anushka Kapoor", "location": "India", "jobRole": "Back-end Developer" },
    { "name": "Ivan Ivanov", "location": "Bulgaria", "jobRole": "Full Stack Developer" },
    { "name": "Alicia García", "location": "Spain", "jobRole": "Database Administrator" },
    { "name": "Hans Schmidt", "location": "Germany", "jobRole": "Network Administrator" },
    { "name": "Sophia Müller", "location": "Germany", "jobRole": "Systems Analyst" },
    { "name": "Andrés López", "location": "Colombia", "jobRole": "Quality Assurance Analyst" },
    { "name": "Valeria Rojas", "location": "Mexico", "jobRole": "Business Analyst" },
    { "name": "Paolo Bianchi", "location": "Italy", "jobRole": "Project Manager" },
    { "name": "Maria Sanchez", "location": "Spain", "jobRole": "Technical Writer" },
    { "name": "Priya Patel", "location": "India", "jobRole": "IT Support Specialist" },
    { "name": "Takahiro Yamamoto", "location": "Japan", "jobRole": "DevOps Engineer" },
    { "name": "Chen Wei", "location": "China", "jobRole": "Cloud Architect" },
    { "name": "Abdel Rahman", "location": "Egypt", "jobRole": "Machine Learning Engineer" },
    { "name": "Marina Petrova", "location": "Russia", "jobRole": "Data Scientist" },
    { "name": "Pedro González", "location": "Mexico", "jobRole": "Cybersecurity Analyst" },
    { "name": "Luiza Silva", "location": "Brazil", "jobRole": "UI Designer" },
    { "name": "Raphael Bernard", "location": "France", "jobRole": "Graphic Designer" },
    { "name": "Lorenzo Rossi", "location": "Italy", "jobRole": "Marketing Manager" },
    { "name": "Ana Maria Fernández", "location": "Spain", "jobRole": "Content Writer" },
  { "name": "Priya Verma", "location": "India", "jobRole": "UX Designer" },
  { "name": "Rahul Sharma", "location": "India", "jobRole": "Software Developer" },
  { "name": "Deepika Singh", "location": "India", "jobRole": "Data Analyst" },
  { "name": "Raj Patel", "location": "India", "jobRole": "Front-end Developer" },
  { "name": "Neha Gupta", "location": "India", "jobRole": "Full Stack Developer" },
  { "name": "Sandeep Kumar", "location": "India", "jobRole": "UI Designer" },
  { "name": "Aman Singh", "location": "India", "jobRole": "Graphic Designer" },
  { "name": "Kiran Sharma", "location": "India", "jobRole": "Marketing Manager" },
  { "name": "Vikas Verma", "location": "India", "jobRole": "Content Writer" },
  { "name": "Aarti Patel", "location": "India", "jobRole": "Social Media Manager" },
  { "name": "Manish Gupta", "location": "India", "jobRole": "Sales Representative" },
  { "name": "Shweta Singh", "location": "India", "jobRole": "Account Manager" },
  { "name": "Rajesh Sharma", "location": "India", "jobRole": "Financial Analyst" },
  { "name": "Shalini Verma", "location": "India", "jobRole": "Human Resources Manager" },
  { "name": "Gaurav Kapoor", "location": "India", "jobRole": "Operations Manager" },
  { "name": "Anjali Singh", "location": "India", "jobRole": "Customer Service Representative" },
  { "name": "Arvind Gupta", "location": "India", "jobRole": "Event Planner" },
  { "name": "Riya Patel", "location": "India", "jobRole": "Logistics Coordinator" },
  { "name": "Akash Sharma", "location": "India", "jobRole": "Supply Chain Analyst" },
  { "name": "Pooja Verma", "location": "India", "jobRole": "Research Analyst" },
  { "name": "Prashant Singh", "location": "India", "jobRole": "Business Development Manager" },
  { "name": "Ananya Kapoor", "location": "India", "jobRole": "UX Researcher" },
  { "name": "Siddharth Kumar", "location": "India", "jobRole": "Mobile App Developer" },
  { "name": "Rajiv Patel", "location": "India", "jobRole": "Systems Administrator" },
  { "name": "Sneha Verma", "location": "India", "jobRole": "UI Developer" },
  { "name": "Aditya Sharma", "location": "India", "jobRole": "IT Consultant" },
  { "name": "Vishal Gupta", "location": "India", "jobRole": "Network Engineer" },
  { "name": "Sanjay Singh", "location": "India", "jobRole": "Data Engineer" },
  { "name": "Sonali Patel", "location": "India", "jobRole": "SEO Specialist" },
  { "name": "Aryan Verma", "location": "India", "jobRole": "Video Editor" },
  { "name": "Kavita Sharma", "location": "India", "jobRole": "Product Designer" },
  { "name": "Yash Kapoor", "location": "India", "jobRole": "E-commerce Manager" },
  { "name": "Juhi Patel", "location": "India", "jobRole": "Digital Marketing Specialist" },
  { "name": "Rajat Gupta", "location": "India", "jobRole": "Artificial Intelligence Engineer" },
  { "name": "Nisha Singh", "location": "India", "jobRole": "Database Developer" },
  { "name": "Ankit Sharma", "location": "India", "jobRole": "IT Project Manager" }
  ]